rainbowkit/__init__.py
rainbowkit/linelist.py
rainbowkit/rainbowkit.py
rainbowkit-0.0.2.dist-info/LICENSE
rainbowkit-0.0.2.dist-info/METADATA
rainbowkit-0.0.2.dist-info/WHEEL
rainbowkit-0.0.2.dist-info/top_level.txt
rainbowkit-0.0.2.dist-info/RECORD
