Metadata-Version: 2.1
Name: rainbowkit
Version: 0.0.2
Summary: Tools to work with spectra
Author-email: Sourav Das <souravdas.sd20@gmail.com>
Classifier: Programming Language :: Python :: 3
Classifier: License :: OSI Approved :: MIT License
Classifier: Operating System :: OS Independent
Requires-Python: >=3.8
License-File: LICENSE
